gmaily/__init__.py
gmaily/gmaily.py
gmaily-0.0.3.dist-info/METADATA
gmaily-0.0.3.dist-info/WHEEL
gmaily-0.0.3.dist-info/top_level.txt
gmaily-0.0.3.dist-info/RECORD
