Metadata-Version: 2.1
Name: gmaily
Version: 0.0.3
Summary: Unofficial Gmail python client with pythonic API.
Home-page: https://github.com/hallazzang/gmaily
Author: Hanjun Kim
Author-email: hallazzang@gmail.com
License: MIT
Platform: UNKNOWN
Classifier: License :: OSI Approved :: MIT License
Classifier: Operating System :: OS Independent
Classifier: Programming Language :: Python :: 3
Classifier: Programming Language :: Python :: 3.5
Classifier: Programming Language :: Python :: 3.6
Classifier: Programming Language :: Python :: 3.7
Classifier: Topic :: Communications :: Email
Classifier: Topic :: Software Development :: Libraries
Classifier: Topic :: Software Development :: Libraries :: Python Modules
Requires-Python: >=3.5
